cleanlab_codex/__about__.py
cleanlab_codex/__init__.py
cleanlab_codex/client.py
cleanlab_codex/project.py
cleanlab_codex/py.typed
cleanlab_codex/experimental/__init__.py
cleanlab_codex/experimental/openai_agents/__init__.py
cleanlab_codex/experimental/openai_agents/cleanlab_hook.py
cleanlab_codex/experimental/openai_agents/utils.py
cleanlab_codex/experimental/strands/README.md
cleanlab_codex/experimental/strands/__init__.py
cleanlab_codex/experimental/strands/cleanlab_model.py
cleanlab_codex/experimental/strands/requirements.txt
cleanlab_codex/internal/__init__.py
cleanlab_codex/internal/analytics.py
cleanlab_codex/internal/organization.py
cleanlab_codex/internal/sdk_client.py
cleanlab_codex/internal/utils.py
cleanlab_codex/internal/validator.py
cleanlab_codex/types/__init__.py
cleanlab_codex/types/organization.py
cleanlab_codex/types/project.py
cleanlab_codex/utils/__init__.py
cleanlab_codex/utils/errors.py
cleanlab_codex/utils/function.py
cleanlab_codex/utils/prompt.py
cleanlab_codex-1.0.33.dist-info/METADATA
cleanlab_codex-1.0.33.dist-info/WHEEL
cleanlab_codex-1.0.33.dist-info/licenses/LICENSE.txt
cleanlab_codex-1.0.33.dist-info/RECORD
