Metadata-Version: 2.4
Name: cleanlab-codex
Version: 1.0.33
Summary: Python client library for developers to integrate Cleanlab Codex into RAG systems
Project-URL: Documentation, https://github.com/cleanlab/cleanlab-codex#readme
Project-URL: Issues, https://github.com/cleanlab/cleanlab-codex/issues
Project-URL: Source, https://github.com/cleanlab/cleanlab-codex
Author-email: Cleanlab Inc <team@cleanlab.ai>
License-Expression: MIT
License-File: LICENSE.txt
Classifier: Development Status :: 5 - Production/Stable
Classifier: Programming Language :: Python
Classifier: Programming Language :: Python :: 3.9
Classifier: Programming Language :: Python :: 3.10
Classifier: Programming Language :: Python :: 3.11
Classifier: Programming Language :: Python :: 3.12
Classifier: Programming Language :: Python :: 3.13
Classifier: Programming Language :: Python :: Implementation :: CPython
Classifier: Programming Language :: Python :: Implementation :: PyPy
Requires-Python: >=3.9
Requires-Dist: cleanlab-tlm>=1.1.14,~=1.1
Requires-Dist: codex-sdk==0.1.0a32
Requires-Dist: pydantic<3,>=2.0.0
